scd2.py
scd2-1.0.0.dist-info/METADATA
scd2-1.0.0.dist-info/WHEEL
scd2-1.0.0.dist-info/top_level.txt
scd2-1.0.0.dist-info/RECORD
