Metadata-Version: 2.1
Name: scd2
Version: 1.0.0
Summary: slowly changing dimension type 2 with pandas or parquet
Home-page: https://gitlab.com/liranc/pandas_scd
Keywords: scd,slowly changing dimension,type 2,pandas,parquet
Requires-Python: >=3.8
Requires-Dist: pandas
Requires-Dist: pyarrow
Requires-Dist: duckdb
